nalcos/__init__.py
nalcos/_version.py
nalcos/get_commits.py
nalcos/get_similar_commits.py
nalcos/nalcos.py
nalcos/utils.py
nalcos-0.2.dist-info/LICENSE
nalcos-0.2.dist-info/METADATA
nalcos-0.2.dist-info/WHEEL
nalcos-0.2.dist-info/entry_points.txt
nalcos-0.2.dist-info/top_level.txt
nalcos-0.2.dist-info/RECORD
