Metadata-Version: 2.1
Name: nalcos
Version: 0.2
Summary: Search Git commits in natural language
Home-page: https://github.com/thepushkarp/nalcos
Author: Pushkar Patel
Author-email: thepushkarp+pypi@gmail.com
License: MIT
Keywords: commit information-retrieval sentence-transformers natural-language huggingface
Platform: UNKNOWN
Classifier: License :: OSI Approved :: MIT License
Classifier: Operating System :: OS Independent
Classifier: Environment :: Console
Classifier: Programming Language :: Python :: 3
Classifier: Programming Language :: Python :: 3.6
Classifier: Programming Language :: Python :: 3.7
Classifier: Programming Language :: Python :: 3.8
Requires-Python: >=3.6
License-File: LICENSE
Requires-Dist: requests (==2.26.0)
Requires-Dist: torch (==1.9.0)
Requires-Dist: sentence-transformers (==2.0.0)
Requires-Dist: appdirs (==1.4.4)
Requires-Dist: transformers (==4.10.1)
Requires-Dist: tqdm (==4.62.1)
Requires-Dist: GitPython (==3.1.18)
Requires-Dist: rich (==10.9.0)
Requires-Dist: black (==19.10b0)
